[
    {
        "design": [
            {
                "src": "https://img.shields.io/badge/Adobe_XD-072326.svg?&style=for-the-badge&logo=Adobe-XD&logoColor=2e3131&color=B7CBCD",
                "alt": "Adobe XD"
            },
            {
                "src": "https://img.shields.io/badge/Adobe_Photoshop-072326.svg?&style=for-the-badge&logo=Adobe-Photoshop&logoColor=2e3131&color=B7CBCD",
                "alt": "Adobe Photoshop"
            },
            {
                "src": "https://img.shields.io/badge/Adobe_InDesign-072326.svg?&style=for-the-badge&logo=Adobe-InDesign&logoColor=2e3131&color=B7CBCD",
                "alt": "Adobe InDesign"
            },
            {
                "src": "https://img.shields.io/badge/Adobe_Illustrator-072326.svg?&style=for-the-badge&logo=Adobe-Illustrator&logoColor=2e3131&color=B7CBCD",
                "alt": "Adobe Illustrator"
            }
        ],
        "development": [
            {
                "src": "https://img.shields.io/badge/HTML-072326.svg?&style=for-the-badge&logo=HTML5&logoColor=2e3131&color=B7CBCD",
                "alt": "HTML"
            },
            {
                "src": "https://img.shields.io/badge/CSS-072326.svg?&style=for-the-badge&logo=CSS3&logoColor=2e3131&color=B7CBCD",
                "alt": "CSS"
            },
            {
                "src": "https://img.shields.io/badge/JavaScript-072326.svg?&style=for-the-badge&logo=Javascript&logoColor=2e3131&color=B7CBCD",
                "alt": "Javascript"
            },
            {
                "src": "https://img.shields.io/badge/PHP-072326.svg?&style=for-the-badge&logo=PHP&logoColor=2e3131&color=B7CBCD",
                "alt": "PHP"
            },
            {
                "src": "https://img.shields.io/badge/React-072326.svg?&style=for-the-badge&logo=React&logoColor=2e3131&color=B7CBCD",
                "alt": "React"
            },
            {
                "src": "https://img.shields.io/badge/VUE-072326.svg?&style=for-the-badge&logo=VUE.JS&logoColor=2e3131&color=B7CBCD",
                "alt": "Vue.js"
            },
            {
                "src": "https://img.shields.io/badge/WordPress-072326.svg?&style=for-the-badge&logo=Wordpress&logoColor=2e3131&color=B7CBCD",
                "alt": "WordPress"
            },
            {
                "src": "https://img.shields.io/badge/Bulma-072326.svg?&style=for-the-badge&logo=Bulma&logoColor=2e3131&color=B7CBCD",
                "alt": "Bulma CSS"
            },
            {
                "src": "https://img.shields.io/badge/Bootstrap-072326.svg?&style=for-the-badge&logo=Bootstrap&logoColor=2e3131&color=B7CBCD",
                "alt": "Bootstrap"
            },
            {
                "src": "https://img.shields.io/badge/Tailwind_CSS-072326.svg?&style=for-the-badge&logo=Tailwind-css&logoColor=2e3131&color=B7CBCD",
                "alt": "Tailwind CSS"
            }
        ]
    }
]